{"id":232863245,"title":"怎樣才可以變成文青","content":"文青\n很潮\n每個都很有個人style\n穿梭在台灣最大城市 台北\n\n要怎樣才能變文青\n有文青可以出來說一下嗎\n謝謝\n\n#文青\n#青色\n#又稱綠藍色\n#是指介於綠色和藍色之間的顏色\n#波長大約為500-485奈米","excerpt":"文青，很潮，每個都很有個人style，穿梭在台灣最大城市 台北，要怎樣才能變文青，有文青可以出來說一下嗎，謝謝，#文青，#青色，#又稱綠藍色，#是指介於綠色和藍色之間的顏色，#波長大約為500-485","anonymousSchool":false,"anonymousDepartment":true,"pinned":false,"forumId":"3c91f2b0-6374-4467-b557-2e5383680afb","replyId":null,"createdAt":"2020-01-10T07:45:49.538Z","updatedAt":"2020-01-10T07:45:49.538Z","commentCount":7,"likeCount":9,"tags":[],"topics":["青色","青澀","ocean是青色","OSN是什麼顏色"],"supportedReactions":null,"withNickname":false,"reportReason":"","hiddenByAuthor":false,"meta":{"layout":"classic"},"forumName":"臺灣大學","forumAlias":"ntu","school":"國立臺灣大學","replyTitle":null,"gender":"M","personaSubscriptable":false,"reactions":[{"id":"286f599c-f86a-4932-82f0-f5a06f1eca03","count":9}],"hidden":false,"customStyle":null,"isSuspiciousAccount":false,"layout":"classic","withImages":false,"withVideos":false,"media":[],"reportReasonText":"","mediaMeta":[],"postAvatar":""}