{"id":232705879,"title":"限定活動🌈【甜蛙】免費外送活動開跑🔥","content":"26度的冬天，\n無論你是躺在宿舍想來一碗冰涼的豆花\n還是在教室裡想用燒仙草撫慰上課的厭世心情QQ\n來囉來囉！\n「甜蛙免費外送服務限定開跑啦🎆」\n\n大家好❤ 我們是輔大企管二年級的學生，\n由於系上的報告需求，\n我們與位於輔大一號出口後面的「甜蛙雪花冰」合作！\n12/18(三) 下午14:00-16:30\n提供快閃外送服務回饋給各位輔大學生❤\n只要消費滿$150 即可免費外送！\n\n趕快和同學一起揪起來🔥\n\n預購表單：\nhttps://forms.gle/XrEDgfZbH3hPRYEZ9\n\n注意事項：\n1. 欲選擇外送服務，請填寫「預購表單」訂購(電話與現場無法享有此服務)\n2. 折價券僅提供現場消費使用\n3. 外送範圍為輔大校園內，且僅能外送到各大樓的一樓\n4. 雪花冰無提供外送服務\n5. 詳細注意事項請詳閱表單！","excerpt":"26度的冬天，無論你是躺在宿舍想來一碗冰涼的豆花，還是在教室裡想用燒仙草撫慰上課的厭世心情QQ，來囉來囉！，「甜蛙免費外送服務限定開跑啦」大家好 我們是輔大企管二年級的學生，由於系上的報告需求，我們與","anonymousSchool":false,"anonymousDepartment":false,"pinned":false,"forumId":"a62a724b-4fdd-4044-b6d3-19483aa7f0df","replyId":null,"createdAt":"2019-12-17T14:38:30.157Z","updatedAt":"2019-12-17T14:38:30.157Z","commentCount":8,"likeCount":67,"tags":[],"topics":["甜蛙","外送","免費","活動","輔大"],"supportedReactions":null,"withNickname":false,"reportReason":"","hiddenByAuthor":false,"meta":{"layout":"classic"},"forumName":"輔仁大學","forumAlias":"fju","school":"輔仁大學","department":"企業管理學系","replyTitle":null,"gender":"F","personaSubscriptable":false,"reactions":[{"id":"286f599c-f86a-4932-82f0-f5a06f1eca03","count":67}],"hidden":false,"customStyle":null,"isSuspiciousAccount":false,"layout":"classic","withImages":false,"withVideos":false,"media":[],"reportReasonText":"","mediaMeta":[],"postAvatar":""}