{"id":232971652,"title":"片# 中文# 父母親出門一日返鄉，我撲倒我可愛的妹妹1天連幹4次","content":"拼命壓抑對妹妹好奇心的哥哥，在妄想下與妹妹的近親相姦生活。\n某天、在浴室洗澡一面好奇一面摸著哥哥的老二被突然闖入的妹妹看到了，覺得噁心又下流把哥哥趕了出去，但是哥哥卻無意間看到闖入的妹妹裸體差點整個大爆發。\n隔天、看到妹妹的電動按摩棒於是進房假借威脅告訴爸媽，除非\"...妳自慰給我看...\"，為了塞住哥哥的嘴，妹妹照作了。但是、哥哥並未對妹妹作出越軌的動作。\n\n天亮了，爸媽因為有事要出門一天，只有我跟哥哥在家。。。時機成熟了！哥哥心中這樣想著。。肉棒也跟著勃起了。。。\n到底會發生什麼事呢…？\n https://tktube.com/videos/1948/0/ \n\nhttp://i.imgur.com/y1bao08.jpg\n\nhttp://i.imgur.com/qmZBuRT.jpg\n\nhttp://i.imgur.com/pXisiId.jpg\n \n#DISALLOW深卡\n#PRIVATE_CONTENT\n我在標籤作了tktube的選項，想要觀看我的影片或者來不及收錄的各位都可以點進去，那邊會找的到。就不會有遺漏的了。","excerpt":"拼命壓抑對妹妹好奇心的哥哥，在妄想下與妹妹的近親相姦生活。某天、在浴室洗澡一面好奇一面摸著哥哥的老二被突然闖入的妹妹看到了，覺得噁心又下流把哥哥趕了出去，但是哥哥卻無意間看到闖入的妹妹裸體差點整個大爆","anonymousSchool":true,"anonymousDepartment":true,"pinned":false,"forumId":"1ce3ebca-8701-42d5-b14c-076fc629bc8e","replyId":null,"createdAt":"2020-01-28T09:18:07.320Z","updatedAt":"2020-01-29T16:00:38.924Z","commentCount":3,"likeCount":304,"tags":[],"topics":["中文字幕","A片","TkTube"],"supportedReactions":null,"withNickname":false,"reportReason":"","hiddenByAuthor":false,"meta":{"layout":"classic","disableAdSense":true},"forumName":"西斯","forumAlias":"sex","replyTitle":null,"gender":"M","personaSubscriptable":false,"reactions":[{"id":"286f599c-f86a-4932-82f0-f5a06f1eca03","count":304}],"hidden":false,"customStyle":null,"isSuspiciousAccount":false,"layout":"classic","withImages":true,"withVideos":false,"media":[{"url":"http://i.imgur.com/y1bao08.jpg"},{"url":"http://i.imgur.com/qmZBuRT.jpg"},{"url":"http://i.imgur.com/pXisiId.jpg"}],"reportReasonText":"","mediaMeta":[{"id":"fe1b7f97-7d22-4270-b0fb-ed44e82a4b95","url":"https://i.imgur.com/y1bao08l.jpg","normalizedUrl":"https://i.imgur.com/y1bao08l.jpg","thumbnail":"https://i.imgur.com/y1bao08l.jpg","type":"image/thumbnail","tags":["NO_NEED_ANNOTATED"],"createdAt":"2020-01-28T09:18:07.320Z","updatedAt":"2020-01-29T16:00:38.924Z"},{"id":"fe1b7f97-7d22-4270-b0fb-ed44e82a4b95","url":"http://i.imgur.com/y1bao08.jpg","normalizedUrl":"https://imgur.com/y1bao08","thumbnail":"https://i.imgur.com/y1bao08l.jpg","type":"image/imgur","tags":["NO_NEED_ANNOTATED"],"createdAt":"2020-01-28T09:18:07.320Z","updatedAt":"2020-01-29T16:00:38.924Z"},{"id":"ea9374df-bb40-4548-a2ac-1df4cc04ae17","url":"http://i.imgur.com/qmZBuRT.jpg","normalizedUrl":"https://imgur.com/qmZBuRT","thumbnail":"https://i.imgur.com/qmZBuRTl.jpg","type":"image/imgur","tags":["NO_NEED_ANNOTATED"],"createdAt":"2020-01-28T09:18:07.320Z","updatedAt":"2020-01-29T16:00:38.924Z"},{"id":"2a69f0ed-0156-4ed8-91d5-525fe9043be2","url":"http://i.imgur.com/pXisiId.jpg","normalizedUrl":"https://imgur.com/pXisiId","thumbnail":"https://i.imgur.com/pXisiIdl.jpg","type":"image/imgur","tags":["NO_NEED_ANNOTATED"],"createdAt":"2020-01-28T09:18:07.320Z","updatedAt":"2020-01-29T16:00:38.924Z"}],"postAvatar":""}