{"id":233004305,"title":"#請益 照片出現紅點需更換鏡頭嗎？","content":"https://megapx-assets.dcard.tw/images/6be91c6f-661a-4581-a9b8-ae93d3906c84/1280.jpeg\n從去年10月多就發現使用前鏡頭時照片會有紅點\n放大後如圖看起來是碎片的樣子？\n請問這是鏡頭壞掉嗎ಥ_ಥ\n一直沒有送修是怕維修時間過長沒手機使用不方便\n目前手機是xr還在保固期內\n但蘋果的官網沒有維修鏡頭的價格\n爬很多文看到有人說原廠維修鏡頭不如直接換新機\n想請問大家會建議送原廠還是外面維修呢？","excerpt":"從去年10月多就發現使用前鏡頭時照片會有紅點，放大後如圖看起來是碎片的樣子？請問這是鏡頭壞掉嗎ಥ_ಥ，一直沒有送修是怕維修時間過長沒手機使用不方便，目前手機是xr還在保固期內，但蘋果的官網沒有維修鏡頭","anonymousSchool":false,"anonymousDepartment":true,"pinned":false,"forumId":"42bfdc63-8601-4e87-b53c-53d831caa2cf","replyId":null,"createdAt":"2020-02-02T17:00:13.145Z","updatedAt":"2020-02-02T17:01:09.516Z","commentCount":4,"likeCount":1,"tags":[],"topics":["紅點","鏡頭","Apple","iPhone","xr"],"supportedReactions":null,"withNickname":false,"reportReason":"","hiddenByAuthor":false,"meta":{"layout":"classic"},"forumName":"Apple","forumAlias":"apple","school":"東吳大學","replyTitle":null,"gender":"F","personaSubscriptable":false,"reactions":[{"id":"286f599c-f86a-4932-82f0-f5a06f1eca03","count":1}],"hidden":false,"customStyle":null,"isSuspiciousAccount":false,"layout":"classic","withImages":true,"withVideos":false,"media":[{"url":"https://megapx-assets.dcard.tw/images/6be91c6f-661a-4581-a9b8-ae93d3906c84/1280.jpeg"}],"reportReasonText":"","mediaMeta":[{"id":"0117fb9f-c7ca-40f6-8c61-bc9631015719","url":"https://megapx-assets.dcard.tw/images/6be91c6f-661a-4581-a9b8-ae93d3906c84/640.jpeg","normalizedUrl":"https://megapx-assets.dcard.tw/images/6be91c6f-661a-4581-a9b8-ae93d3906c84/640.jpeg","thumbnail":"https://megapx-assets.dcard.tw/images/6be91c6f-661a-4581-a9b8-ae93d3906c84/640.jpeg","type":"image/thumbnail","tags":["ANNOTATED"],"createdAt":"2020-02-02T17:00:13.145Z","updatedAt":"2020-02-02T17:01:09.516Z","width":296,"height":640},{"id":"0117fb9f-c7ca-40f6-8c61-bc9631015719","url":"https://megapx-assets.dcard.tw/images/6be91c6f-661a-4581-a9b8-ae93d3906c84/1280.jpeg","normalizedUrl":"https://megapx.dcard.tw/v1/images/6be91c6f-661a-4581-a9b8-ae93d3906c84","thumbnail":"https://megapx-assets.dcard.tw/images/6be91c6f-661a-4581-a9b8-ae93d3906c84/640.jpeg","type":"image/megapx","tags":["ANNOTATED"],"createdAt":"2020-02-02T17:00:13.145Z","updatedAt":"2020-02-02T17:01:09.516Z","width":828,"height":1792}],"postAvatar":""}