{"id":232724956,"title":"推薦甜文💓刷卡單太長了懶得慢慢滑","content":"嘿～一樣老規矩～\n🎈本人不愛古裝、穿越、BL，所以書單無此類小說\n🎈書單指示（依我看完的感受分類）：\n💛我極喜歡，願意再回頭幾刷\n💙我喜歡，有機會回頭幾刷\n（空白）還可以，普普\n💔看的過程讓我想棄，或結局不愛 \n\n\\大推😋/\n💛他來了，請閉眼/丁墨：簡瑤、薄靳言\n💛如果蝸牛有愛情/丁墨：許詡、季白\n💛美人為餡/丁墨：蘇眠、韓沉\n💡美人為餡>他來了，請閉眼>如果蝸牛有愛情\n \n💙（校）今日宜喜歡/六盲星：傅今栩、邵寒越\n💙（校）每天上課都被懟/灼夜：沈汐、薛焱\n💙（校）老師來了叫我喔/畫盞眠：江甜、陸允信\n💙（校）小尾巴很甜/顏溫：唐溫、許珩年\n💙（校）然後是你/阿淳：蒔音、裴時榿\n💙（校）他的小雀躍/優莉：林雀、鹿鳴\n💙（校）我罩著你呀/阿淳：初願、江行燁\n 💙奈何只鍾情於你/甜糖：沈繁繁、周子昀\n💙如果月亮不抱你/六盲星：岑寧、言行之\n💙掌心寵愛/時星草：易晨曦、賀川\n💙一入豪門出不來/義玥公子：岳清瑤、蕭政宇\n💙少加一點糖/六盲星：許珂、肖期\n💙他說的我都聽/六盲星：程思眠、蘇顯言\n💙照見星星的他/隨侯珠：湯貝貝、沈時\n💙就這樣戀著你/夢筱二：夏沐、紀羨北\n💙他來時有曙光/陌言川：秦棠、蔣川\n💙她很不討喜/宋玖槿：陸熙禾、紀衍\n💙生薑紅糖/深海與月光：唐以夢、姜炎\n💙在暴雪時分/墨寶非寶：殷果、林亦揚\n💙艷域/沐清雨：蕭語衍、馮普驍\n💙不小心坐了影帝大腿/一字眉：姜沅、凌霍\n \n（校）她是我的姑娘/星球酥：顧關山、沈澤\n（校）仙女味的她/周嘉禾：阮心、林深\n（校）再皮一下就親你/一字眉：沈都清、江峙\n（校）藏在我心底的你/張不一：李西寧、陸宇翎\n（軍）半生熟/沐清雨：賀熹、厲行\n（軍）塵光舊夢／墨末：葉知夢、趙京寧\n（軍）我彧歸來/筱露：蘇安希、徐彧\n（軍）只有我懂他的柔情/陌言川：明燭、陸焯峰 \n你老婆掉了/六盲星：鹿桑桑、段敬懷\n你聽得到/桑玠：柯姣、謝修弋\n黏你成癮/舒虞：蘇漿、徐斯澤\n莫負寒夏/丁墨：木寒夏、林莫臣\n他來了請閉眼之暗粼/丁墨：簡瑤、薄靳言\n花瓶專業戶/陌言川：景心、秦森\n廝磨/孟宋：喬眠、沈雲黎\n上司攻略/七分塵：彭佳音、肖以森\n一點即然/陌言川：周宜寧、季東陽\n待你心裡不挪窩/舒虞：易胭、蘇岸\n南北往事/長宇宙：霍皙、沈斯亮\n我來得稍稍遲/灰調子貓：余彤、談遇\n等/貝曉莞：任珂、程等\n初見情深/時星草：姜映初、顧修竹\n就等你下課了/灼夜：盛微語、易言\n睡夠了沒/栖見：時吟、顧從禮\n頭號纏人精/玄宓：付洒洒、聞泱\n歸鹿/宋玖槿：江鹿、陳洲\n他有溫暖眉眼/酥軟：陳溺、許塵深\n他似星辰大海/畫盞眠：霍星葉、楚珣\n他先動的心/圖樣先森：褚漾、徐南燁\n \n💔慈悲城\n💔許妳甜糖時光\n\n下台一鞠躬～\n希望大家能多多捐獻口袋名單給我，正值書荒ing 555","excerpt":"嘿～一樣老規矩～本人不愛古裝、穿越、BL，所以書單無此類小說，書單指示（依我看完的感受分類）：我極喜歡，願意再回頭幾刷，我喜歡，有機會回頭幾刷，（空白）還可以，普普，看的過程讓我想棄，或結局不愛，\\大","anonymousSchool":false,"anonymousDepartment":true,"pinned":false,"forumId":"e0a290f4-752b-48a2-a791-f211f8b46588","replyId":230739746,"createdAt":"2019-12-20T07:36:23.312Z","updatedAt":"2019-12-20T07:48:49.566Z","commentCount":10,"likeCount":180,"tags":["HIDE_THUMBNAIL"],"topics":["小說","言情小說","推薦書單"],"supportedReactions":null,"withNickname":false,"reportReason":"","hiddenByAuthor":false,"meta":{"layout":"classic"},"forumName":"書籍","forumAlias":"book","school":"銘傳大學","replyTitle":"（3更-增）推薦甜文💕跟刷卡單一樣長的書單","gender":"F","personaSubscriptable":false,"reactions":[{"id":"286f599c-f86a-4932-82f0-f5a06f1eca03","count":180}],"hidden":false,"customStyle":null,"isSuspiciousAccount":false,"layout":"classic","withImages":false,"withVideos":false,"media":[],"reportReasonText":"","mediaMeta":[],"postAvatar":""}