{"id":232733947,"title":"洗衣精","content":"自從住外面後 我每次洗衣服後都會看到衣服上有一塊一塊的洗衣精殘留在上面\n可是我已經把洗衣精的量減少很多了\n還是會這樣\n以前住宿舍用宿舍的洗衣機洗就沒這樣\n想請問有人知道這是為什麼嗎\n要怎麼解決這個問題呢QQ\n(我沒放柔軟精","excerpt":"自從住外面後 我每次洗衣服後都會看到衣服上有一塊一塊的洗衣精殘留在上面，可是我已經把洗衣精的量減少很多了，還是會這樣，以前住宿舍用宿舍的洗衣機洗就沒這樣，想請問有人知道這是為什麼嗎，要怎麼解決這個問題","anonymousSchool":false,"anonymousDepartment":true,"pinned":false,"forumId":"5b964198-2e59-419d-b44c-0276d0fea7e8","replyId":null,"createdAt":"2019-12-21T16:05:57.344Z","updatedAt":"2019-12-21T16:05:57.344Z","commentCount":10,"likeCount":7,"tags":[],"topics":["洗衣"],"supportedReactions":null,"withNickname":false,"reportReason":"","hiddenByAuthor":false,"meta":{"layout":"classic"},"forumName":"居家生活","forumAlias":"house","school":"東海大學","replyTitle":null,"gender":"F","personaSubscriptable":false,"reactions":[{"id":"286f599c-f86a-4932-82f0-f5a06f1eca03","count":7}],"hidden":false,"customStyle":null,"isSuspiciousAccount":false,"layout":"classic","withImages":false,"withVideos":false,"media":[],"reportReasonText":"","mediaMeta":[],"postAvatar":""}