{"id":232551129,"title":"霸凌者的心態","content":"會霸凌別人的人通常心態都很驕傲\n他們就是想彰顯自己很厲害通常他們的人緣都很好，目的他們就是想讓別人知道他們很了不起，這樣才能讓他人認為沒人敢反抗抵制他們\n多數的霸凌者是自我膨脹的，自我感覺良好的。藉由羞辱他人來獲得一定的自尊心，認為自己霸凌排擠別人沒有錯，還把錯都怪在別人身上。霸凌者就說都是那個人的錯，到處跟別人說都是那個人行為怪異或者是四處說那個人的壞話，讓大家漸漸認為那個人就是霸凌者所說的那個人，霸凌者就可以合理化自己排擠別人的行為，把自己的錯都推到被排擠者。還會亂誣賴別人有毛病，頭腦有問題之類的。被被排擠者反抗回去就被周遭的人認為真的是這樣。害的他只能默默被辱罵。然而被排擠者就這樣被誤會了，沒人願意在和他有任何交集，不想做他朋友，霸凌者持續辱罵，最終毀掉一個人的大學人生甚至是未來，造成他一輩子的陰影及恐懼，這是會影響一輩子的，難道霸凌者在排擠別人之前都不能將心比心嗎，一定要這樣搞，毀掉他人的人生他們就很爽，這是什麼變態的心裡啊？","excerpt":"會霸凌別人的人通常心態都很驕傲，他們就是想彰顯自己很厲害通常他們的人緣都很好，目的他們就是想讓別人知道他們很了不起，這樣才能讓他人認為沒人敢反抗抵制他們，多數的霸凌者是自我膨脹的，自我感覺良好的。藉由","anonymousSchool":false,"anonymousDepartment":false,"pinned":false,"forumId":"cd2959fe-5515-4c1e-bd35-1cd4c36b44f0","replyId":null,"createdAt":"2019-11-22T11:09:11.043Z","updatedAt":"2019-11-22T11:15:48.845Z","commentCount":27,"likeCount":25,"tags":[],"topics":["霸凌","心態","大學","明志科大","大學生"],"supportedReactions":null,"withNickname":false,"reportReason":"","hiddenByAuthor":false,"meta":{"layout":"classic"},"forumName":"新生季","forumAlias":"freshman","school":"明志科技大學","department":"機械工程系","replyTitle":null,"gender":"M","personaSubscriptable":false,"reactions":[{"id":"286f599c-f86a-4932-82f0-f5a06f1eca03","count":22},{"id":"514c2569-fd53-4d9d-a415-bf0f88e7329f","count":2},{"id":"e8e6bc5d-41b0-4129-b134-97507523d7ff","count":1}],"hidden":false,"customStyle":null,"isSuspiciousAccount":false,"layout":"classic","withImages":false,"withVideos":false,"media":[],"reportReasonText":"","mediaMeta":[],"postAvatar":""}