{"id":232918688,"title":"求雙北好吃雞蛋糕","content":"先跟大家分享♡\n自己吃過的雞蛋糕店\n1.士林華榮市場口雞蛋糕\n這家是我從小吃到大的啦!還記得以前陪阿嬤來逛市場都吵著要吃這家雞蛋糕 有可愛圖案的跟蛋型的~綜合的兩種一次滿足啦😊這家雞蛋糕吃起來不會太甜又軟軟的 我記得應該是一份8個25塊 這根本不是台北的價格啊!!!!! 充滿回憶的雞蛋糕😍(偷偷提醒大家先做的最好吃 但老闆有時候會做一堆放著😢)\n\n2.魚刺人雞蛋糕(南西＆樂華)\n魚刺人的紅茶口味真的無人能敵 滿滿的茶葉香跟脆脆的外皮 是我心目中第一名的雞蛋糕😗我自己是覺得南西店＞樂華店 但是現在兩家都沒開了 台北沒有其他分店了(ಥ_ಥ)  所以才上來跟大家求救找台北好吃的雞蛋糕店...\n\n3.士林夜市 大熊雞蛋糕\n這家雞蛋糕的口味有很多特別的像麻糬啊或是起司玉米起司火腿~也有比較常見的原味或是巧克力 這家是我吃過最紮實的雞蛋糕 原味的有濃濃的蛋香跟超脆的皮 如果想要焦脆一點的皮還可以特別跟老闆說! 可惜這家老闆說不敷成本後來改開果汁店了😢😢😢😢\n\n4.忠孝敦化 金蛋糕\n金蛋糕在忠孝敦化站六號出口旁邊 蛋糕形狀是比較特別的長條型 沒有分口味但大家都一次買超多的Σ(°Д°; 經過旁邊就會覺得超級超級香 忍不住走過去買一份 蛋糕本身吃起來有一點檸檬或是柑橘類香香的味道 比較不會一下子就吃膩了🍊\n\n希望大家也可以推薦我雙北其他好吃的雞蛋糕(*¯︶¯*)","excerpt":"先跟大家分享，自己吃過的雞蛋糕店，1.士林華榮市場口雞蛋糕，這家是我從小吃到大的啦！還記得以前陪阿嬤來逛市場都吵著要吃這家雞蛋糕 有可愛圖案的跟蛋型的~綜合的兩種一次滿足啦這家雞蛋糕吃起來不會太甜又軟","anonymousSchool":false,"anonymousDepartment":true,"pinned":false,"forumId":"de977130-f3eb-467b-822e-b0e91124e9eb","replyId":null,"createdAt":"2020-01-19T08:13:34.292Z","updatedAt":"2020-01-19T15:25:38.054Z","commentCount":18,"likeCount":26,"tags":[],"topics":["雞蛋糕"],"supportedReactions":null,"withNickname":false,"reportReason":"","hiddenByAuthor":false,"meta":{"layout":"classic"},"forumName":"美食","forumAlias":"food","school":"國立臺北大學","replyTitle":null,"gender":"F","personaSubscriptable":false,"reactions":[{"id":"286f599c-f86a-4932-82f0-f5a06f1eca03","count":26}],"hidden":false,"customStyle":null,"isSuspiciousAccount":false,"layout":"classic","withImages":false,"withVideos":false,"media":[],"reportReasonText":"","mediaMeta":[],"postAvatar":""}