{"id":232329290,"title":"#問 北海道語言學校、打工換宿、生活","content":"我預計明年去北海道讀半年語言學校之後去牧場、農場、滑雪場打工換宿，現在已申請打工簽，日語自學今年7月剛考到N3，12月要考N2，目前想去兩家札幌的語言學校(各讀三個月)\n\n第一間是： 北海道日本語学院 札幌本校 Hokkaido Japanese Language Academy Sapporo Main Campus \n這間網路上資訊很少，網站對於課程內容也沒有很多說明，所以想請教有沒有前輩讀過這間可以分享一下學校的課程如何以及宿舍的狀況?\n\n第二間是： 北海道ジャパニーズランゲージスクール \n這間網路上比較多資訊，諮詢的代辦說這間著重會話練習，還有實習的課程，但費用比較貴比第一間貴將近兩倍，住宿的部分分寄宿家庭、share house、周租公寓、旅館，我個人是排除旅館的選項，但另外三種很猶豫，寄宿家庭交通距離遠、share house怕遇到可怕室友、周租公寓比較貴生活也可能比較孤單，另外代辦又說他認為讀第二間學校自己租房子比較好(但感覺手續很複雜)。想問讀過這間的前輩能不能分享一下學校課程狀況?住宿的部分有沒有什麼建議?\n\n最後想問在北海道的生活有什麼相關的建議，因為之前爬文看到一定要買加濕器(我剛好喉嚨很容易發炎)，還有如果要自己租房子有沒有相關的管道或是方式提供?如果要邊念語言學校邊打工，有沒有前輩可以分享一下自己的經驗?\n\n問題很多不好意思，謝謝。","excerpt":"我預計明年去北海道讀半年語言學校之後去牧場、農場、滑雪場打工換宿，現在已申請打工簽，日語自學今年7月剛考到N3，12月要考N2，目前想去兩家札幌的語言學校（各讀三個月），第一間是： 北海道日本語学院 ","anonymousSchool":false,"anonymousDepartment":true,"pinned":false,"forumId":"ee51d6cd-ad7e-4d73-b79a-3ce32ea7798b","replyId":null,"createdAt":"2019-10-19T05:44:55.066Z","updatedAt":"2019-10-19T05:44:55.066Z","commentCount":0,"likeCount":15,"tags":[],"topics":["日本生活","日本留學","打工度假","日語"],"supportedReactions":null,"withNickname":false,"reportReason":"","hiddenByAuthor":false,"meta":{"layout":"classic"},"forumName":"日本生活","forumAlias":"japan_life","school":"中原大學","replyTitle":null,"gender":"F","personaSubscriptable":false,"reactions":[{"id":"286f599c-f86a-4932-82f0-f5a06f1eca03","count":15}],"hidden":false,"customStyle":null,"isSuspiciousAccount":false,"layout":"classic","withImages":false,"withVideos":false,"media":[],"reportReasonText":"","mediaMeta":[],"postAvatar":""}