{"id":232738248,"title":"日本醫療通譯者","content":"我是一名護理師\n對日本文化也很有興趣\n目前有N3程度 明年要考N2\n日文我完全是自學 完全沒去補習過\n\n因為真的很想利用打工簽證方式到日本看看\n又偶然在搜尋打工時 看到居然有醫療通譯員這份工作\n以前聽我姑姑(住在日本)說，現在日本很歡迎中國的有錢人到他們那裡做超貴的健康檢查 以此來賺錢。\n我就在想 是不是這個原因 所以才有這個職務。\n\n因為我也搞不太清楚，上網找資訊也不多，所以想請問在日本生活的各位，知道這類型的工作相關的注意事項嗎？","excerpt":"我是一名護理師，對日本文化也很有興趣，目前有N3程度 明年要考N2，日文我完全是自學 完全沒去補習過，因為真的很想利用打工簽證方式到日本看看，又偶然在搜尋打工時 看到居然有醫療通譯員這份工作，以前聽我","anonymousSchool":false,"anonymousDepartment":false,"pinned":false,"forumId":"ee51d6cd-ad7e-4d73-b79a-3ce32ea7798b","replyId":null,"createdAt":"2019-12-22T11:44:20.926Z","updatedAt":"2019-12-22T12:12:57.052Z","commentCount":3,"likeCount":5,"tags":[],"topics":["醫療","日本","日本工作"],"supportedReactions":null,"withNickname":true,"reportReason":"","hiddenByAuthor":false,"meta":{"layout":"classic"},"forumName":"日本生活","forumAlias":"japan_life","school":"丸子","department":"maggie_lala","replyTitle":null,"gender":"F","personaSubscriptable":null,"reactions":[{"id":"286f599c-f86a-4932-82f0-f5a06f1eca03","count":5}],"hidden":false,"customStyle":null,"isSuspiciousAccount":false,"layout":"classic","withImages":false,"withVideos":false,"media":[],"reportReasonText":"","mediaMeta":[],"postAvatar":""}