{"id":232920862,"title":"行動數據無預警斷線","content":"從前天開始iphone 8 plus 會無預警斷線 一開始解決方法是重置網路設定後或重新開機網路就可以使用 後來去詢問蘋果客服 他說要重置整台手機我重置完後 還是會發生這樣的狀況 開飛航 行動數據關掉重開一樣有同樣狀況 最近一到兩天才開始發生 一天大概會斷一次 各位有遇過嗎 有什麼比較好的解決辦法","excerpt":"從前天開始iphone 8 plus 會無預警斷線 一開始解決方法是重置網路設定後或重新開機網路就可以使用 後來去詢問蘋果客服 他說要重置整台手機我重置完後 還是會發生這樣的狀況 開飛航 行動數據關掉","anonymousSchool":false,"anonymousDepartment":false,"pinned":false,"forumId":"42bfdc63-8601-4e87-b53c-53d831caa2cf","replyId":null,"createdAt":"2020-01-19T14:43:01.777Z","updatedAt":"2020-01-19T14:43:01.777Z","commentCount":4,"likeCount":1,"tags":[],"topics":["iPhone"],"supportedReactions":null,"withNickname":false,"reportReason":"","hiddenByAuthor":false,"meta":{"layout":"classic"},"forumName":"Apple","forumAlias":"apple","school":"國立高雄大學","department":"電機工程學系","replyTitle":null,"gender":"M","personaSubscriptable":false,"reactions":[{"id":"aa0d425f-d530-4478-9a77-fe3aedc79eea","count":1}],"hidden":false,"customStyle":null,"isSuspiciousAccount":false,"layout":"classic","withImages":false,"withVideos":false,"media":[],"reportReasonText":"","mediaMeta":[],"postAvatar":""}