{"id":232975295,"title":"想見你","content":"想念離我如此之近 才發現你遙不可及\n\n你的出現 就足夠佔有我餘生那些\n\n失去你的時間裡面\n我的世界未往前\n\n所有的離別都是我在練習失去你\n\n要我怎麼穿越時間 重新和你相遇一遍\n\n在想念的時候 就把溫柔的自己用完了\n\n慢慢把自己擱淺在無法拼湊的昨天\n\n希望有一天這個世界會變得不一樣\n不管我喜歡誰 都不再奇怪\n有些喜歡能夠穿越時間 依然來到你面前\n\n你一不小心就掉落進我的夢裡\n\n我寧願這樣記得 你從未離開過我的世界\n\nOnly if you ask to see me\nOur meeting will be meaningful to me\n-\n2年了\n在那之後從來沒有任何的交談 言語\n我只知道你在密室打工\n不知道你現在還在不在\n我好想對你說\n對不起\n我後悔了\n我希望我們還能是朋友\n當初我到底在想什麼\n過年大家\n胖的沒人愛\n胖的很可愛\n我在歐洲不會胖\n愛你的我\n你感受得到嗎~\n如果時光能倒流\n我還想再見你一面\nhttps://megapx-assets.dcard.tw/images/81eae826-18bc-4513-ad61-db2489e1dc33/1280.jpeg\n-\n#以上佳句取自想見你","excerpt":"想念離我如此之近 才發現你遙不可及，你的出現 就足夠佔有我餘生那些，失去你的時間裡面，我的世界未往前，所有的離別都是我在練習失去你，要我怎麼穿越時間 重新和你相遇一遍，在想念的時候 就把溫柔的自己用完","anonymousSchool":true,"anonymousDepartment":true,"pinned":false,"forumId":"b5b2653a-6304-4564-9ea0-a4cec0be7aee","replyId":null,"createdAt":"2020-01-28T19:49:54.027Z","updatedAt":"2020-01-28T19:50:45.129Z","commentCount":4,"likeCount":74,"tags":[],"topics":["Les","想見你","獅子","射手"],"supportedReactions":null,"withNickname":false,"reportReason":"","hiddenByAuthor":false,"meta":{"layout":"classic"},"forumName":"彩虹","forumAlias":"rainbow","replyTitle":null,"gender":"F","personaSubscriptable":true,"reactions":[{"id":"286f599c-f86a-4932-82f0-f5a06f1eca03","count":74}],"hidden":false,"customStyle":null,"isSuspiciousAccount":false,"layout":"classic","withImages":true,"withVideos":false,"media":[{"url":"https://megapx-assets.dcard.tw/images/81eae826-18bc-4513-ad61-db2489e1dc33/1280.jpeg"}],"reportReasonText":"","mediaMeta":[{"id":"a02109df-12d3-4abf-92b9-4ebb2e469530","url":"https://megapx-assets.dcard.tw/images/81eae826-18bc-4513-ad61-db2489e1dc33/640.jpeg","normalizedUrl":"https://megapx-assets.dcard.tw/images/81eae826-18bc-4513-ad61-db2489e1dc33/640.jpeg","thumbnail":"https://megapx-assets.dcard.tw/images/81eae826-18bc-4513-ad61-db2489e1dc33/640.jpeg","type":"image/thumbnail","tags":["ANNOTATED"],"createdAt":"2020-01-28T19:49:54.027Z","updatedAt":"2020-01-28T19:50:45.129Z","width":296,"height":640},{"id":"a02109df-12d3-4abf-92b9-4ebb2e469530","url":"https://megapx-assets.dcard.tw/images/81eae826-18bc-4513-ad61-db2489e1dc33/1280.jpeg","normalizedUrl":"https://megapx.dcard.tw/v1/images/81eae826-18bc-4513-ad61-db2489e1dc33","thumbnail":"https://megapx-assets.dcard.tw/images/81eae826-18bc-4513-ad61-db2489e1dc33/640.jpeg","type":"image/megapx","tags":["ANNOTATED"],"createdAt":"2020-01-28T19:49:54.027Z","updatedAt":"2020-01-28T19:50:45.129Z","width":924,"height":2000}],"postAvatar":""}