{"id":232964066,"title":"學歷的差距要怎麼填補","content":"這算是一段時間都要出現一次的月經文了吧XD\n\n女友是北部國立某頂大的 我是私立學店\n讀這間學校自己要負大多數的責任\n另一部分是因為家人不希望我再重考\n沒什麼好說的\n\n出社會後發現薪水永遠少領別人幾萬 \n雖然想換工作  但收到的面試邀請 薪資卻沒比現在的好\n\n女友年紀比我小 領著比我高的薪水 說實話內心有點慌\n她常常撒嬌說要給我養(半真半假吧)\n我笑著說不是應該你養我嗎 賺比我多耶\n內心想的是 我想養也養不起你啊ಥ_ಥ\n想要跟上她的腳步卻覺得很遙遠\n因為自卑 所以想問卻問不出口的問題是：為什麼是我？\n\n跟女友算是很契合 交往一年多以來\n還沒有什麼激烈爭吵 大多數時候都能好好講開\n興趣也很類似 生活上也沒太多要磨合的\n這些原因足夠讓人無視那些差距嗎\n\n我隱約有一種好像不充實自己\n總有一天會被丟下的不安全感\n也不知道會不會有追上的那一天\n雖然解鈴還須繫鈴人 \n但忍不住想上來聽聽其他人的看法","excerpt":"這算是一段時間都要出現一次的月經文了吧XD，女友是北部國立某頂大的 我是私立學店，讀這間學校自己要負大多數的責任，另一部分是因為家人不希望我再重考，沒什麼好說的，出社會後發現薪水永遠少領別人幾萬，雖然","anonymousSchool":true,"anonymousDepartment":true,"pinned":false,"forumId":"b5b2653a-6304-4564-9ea0-a4cec0be7aee","replyId":null,"createdAt":"2020-01-26T20:41:26.683Z","updatedAt":"2020-01-26T20:42:43.078Z","commentCount":17,"likeCount":81,"tags":["HIDE_THUMBNAIL"],"topics":[],"supportedReactions":null,"withNickname":false,"reportReason":"","hiddenByAuthor":false,"meta":{"layout":"classic"},"forumName":"彩虹","forumAlias":"rainbow","replyTitle":null,"gender":"F","personaSubscriptable":null,"reactions":[{"id":"286f599c-f86a-4932-82f0-f5a06f1eca03","count":81}],"hidden":false,"customStyle":null,"isSuspiciousAccount":false,"layout":"classic","withImages":false,"withVideos":false,"media":[],"reportReasonText":"","mediaMeta":[],"postAvatar":""}