{"id":232913777,"title":"請各位幫幫忙，延續咕嚕強韌的生命力 幫忙轉發謝謝","content":"持續更新中\n\n留言區會放更新狀況影片及照片，謝謝大家的關心♥️\n\n咕嚕從一個月大的時候，就被母貓遺棄在垃圾場，那時一共有兩隻，而另一隻幼幼在我們發現時已經當了小天使....這時我們注意到了一旁還有一隻有生命跡象，也就是咕嚕.....他堅強不屈於現實的生命力，讓我們注意到他，並且帶他去醫院檢查治療。\n\n小小年紀的時候他的眼睛就這樣感染，且非常嚴重，實在不知道牠是如何撐過來的，連醫生都讚嘆他強大的生命力！\n\n那時的檢查結果顯示，咕嚕到兩顆眼睛嚴重感染，但年紀還太小，只能用藥物先控制。現在咕嚕已經一歲了，但他的眼睛，只有一隻成功的用藥物治療，另一隻已經壞死且需要摘除...\n\n不幸的是現在咕嚕的眼睛有化膿的跡象，醫生說需要緊急開刀，需要龐大的醫療費用，希望各位善心的朋友，可以發揮愛心，醫療費用是一萬五。\n\n目前咕嚕已在醫院治療，每個人1000元也好500也好，請大家做咕嚕的愛心天使幫助咕嚕延續他強韌的生命，請大家共襄盛舉！\n\nhttps://i.imgur.com/SCJxO4Z.jpg\n\n\n費用明細：\n術前檢查（驗血、電解質、X光）-2600\n手術費用（含麻醉、縫合）-6200\n術後補充（補血劑、住院費用（一星期）、藥費）-5350\n術後檢查（驗血、測眼壓）-1300\n\n後續感染檢查醫療-9700\n（血液化驗、抗生素、藥費、住院）\n📌後續檢查會陸陸續續有衍生費用，那這邊也會一個一個向各位朋友報告咕嚕的現況！謝謝大家的幫助，我相信咕嚕一定可以好起來！\n\nhttps://www.dcard.tw/v2/vivid/videos/b7aef0d1-c9b6-49ef-ba0d-32b89627353d?r=0.5625\n\n\n醫療金費有朋友願意借我先付手術費用，這筆費用仍需歸還，借貸金額為12000。\n\n中國信託捐款帳號：381540481675 \n捐款前請先私訊我，謝謝你們！\n\n感謝以下愛心天使的付出：\nJoanna Yang-500\n阿寶-1000\n林明-1000\n匿名愛心天使-2000\n匿名愛心天使-1000\n賴宜靖-1000\n匿名愛心天使-800\n匿名愛心天使-1000\n匿名愛心天使-2000\n蔡宜仁-1000\n匿名愛心天使-100\n匿名愛心天使-1000\n匿名愛心天使-2000\n匿名愛心天使-1000\n進度：15400/24700\n\n#麻煩有捐款請一定要先私訊我\n#我想知道是誰幫助了我們\n#謝謝你們\n\n更新：\n咕嚕手術已經結束了，現在平安！也謝謝各位的愛心！\n\n1/15\n醫生說咕嚕有感染跡象，且發燒了，那目前已經退燒，後續要在做檢查，確認感染的病毒或細菌是什麼才能進一步治療。\n\n1/16\n血液化驗，結果三天後才會出來。\n\n1/17\n檢驗報告週一出來，咕嚕目前食慾還是很差，而且持續有打噴嚏的症狀。等週一報告出來後，醫生會在做進一步的治療！\n\n1/18\n食慾稍微好一點，會吃但不多...\n醫生說要看報告禮拜一趕不趕的出來\n\n持續更新中","excerpt":"持續更新中，留言區會放更新狀況影片及照片，謝謝大家的關心️，咕嚕從一個月大的時候，就被母貓遺棄在垃圾場，那時一共有兩隻，而另一隻幼幼在我們發現時已經當了小天使....這時我們注意到了一旁還有一隻有生命","anonymousSchool":false,"anonymousDepartment":false,"pinned":false,"forumId":"7ee21581-1307-4ba9-b9dc-82028bdcca49","replyId":null,"createdAt":"2020-01-18T11:21:19.958Z","updatedAt":"2020-01-18T11:58:34.123Z","commentCount":6,"likeCount":23,"tags":[],"topics":["貓","募款","寵物","米克斯","領養代替購買"],"supportedReactions":null,"withNickname":false,"reportReason":"","hiddenByAuthor":false,"meta":{"layout":"classic"},"forumName":"寵物","forumAlias":"pet","school":"南臺科技大學","department":"多媒體與電腦娛樂科學系","replyTitle":null,"gender":"F","personaSubscriptable":null,"reactions":[{"id":"286f599c-f86a-4932-82f0-f5a06f1eca03","count":22},{"id":"514c2569-fd53-4d9d-a415-bf0f88e7329f","count":1}],"hidden":false,"customStyle":null,"isSuspiciousAccount":false,"layout":"classic","withImages":true,"withVideos":true,"media":[{"url":"https://i.imgur.com/SCJxO4Z.jpg"},{"url":"https://vivid.dcard.tw/Public/b7aef0d1-c9b6-49ef-ba0d-32b89627353d/thumbnail.jpg"}],"reportReasonText":"","mediaMeta":[{"id":"eab5157b-7956-4b40-bd83-b73d4b6bbc81","url":"https://i.imgur.com/SCJxO4Zl.jpg","normalizedUrl":"https://i.imgur.com/SCJxO4Zl.jpg","thumbnail":"https://i.imgur.com/SCJxO4Zl.jpg","type":"image/thumbnail","tags":["ANNOTATED"],"createdAt":"2020-01-18T11:58:34.123Z","updatedAt":"2020-01-18T11:58:34.123Z"},{"id":"eab5157b-7956-4b40-bd83-b73d4b6bbc81","url":"https://i.imgur.com/SCJxO4Z.jpg","normalizedUrl":"https://imgur.com/SCJxO4Z","thumbnail":"https://i.imgur.com/SCJxO4Zl.jpg","type":"image/imgur","tags":["ANNOTATED"],"createdAt":"2020-01-18T11:58:34.123Z","updatedAt":"2020-01-18T11:58:34.123Z"},{"id":"81d247dc-df31-40fa-9012-cc3ef35d357b","url":"https://www.dcard.tw/v2/vivid/videos/b7aef0d1-c9b6-49ef-ba0d-32b89627353d?r=0.5625","normalizedUrl":"","thumbnail":"https://vivid.dcard.tw/Public/b7aef0d1-c9b6-49ef-ba0d-32b89627353d/thumbnail.jpg","type":"video/vivid","tags":["ANNOTATED_FAILED"],"createdAt":"2020-01-18T11:21:19.958Z","updatedAt":"2020-01-18T11:58:34.123Z"}],"postAvatar":""}