{"id":232123962,"title":"綠蛇蛇","content":"聽說Po色違文要充實內容，那我就好好（充實）吧\n\n大岩蛇色違剛推出時，就非常想要\n那時忘記是哪個限定田野任務了，每天都去解任務，但活動結束都沒色\n\n接著關注巢穴及解連續3次great，一樣一直色不了！\n上星期中秋回高雄，剛好澄清湖是大岩蛇的巢穴，馬上安排行程前往，但（依舊沒有）\n\n這星期換巢穴了，剛好台北宿舍附近的「榮星花園」正式大岩蛇巢穴，下班後立即前往，，抓沒幾隻，終於色了\n\n累積起來至少破百隻才遇到\n\nhttps://i.imgur.com/LOhiOET.png\nhttps://i.imgur.com/gms2BJq.png\nhttps://i.imgur.com/3yPbWNB.png\n\nPS：大找有色違機率，不過我還是覺得看看就好\n，遇色違完全看緣分，再遇到之前，就是多遇多抓了","excerpt":"聽說Po色違文要充實內容，那我就好好（充實）吧，大岩蛇色違剛推出時，就非常想要，那時忘記是哪個限定田野任務了，每天都去解任務，但活動結束都沒色，接著關注巢穴及解連續3次great，一樣一直色不了！，上","anonymousSchool":false,"anonymousDepartment":false,"pinned":false,"forumId":"99049f5e-bb3d-420f-b708-52c384359952","replyId":null,"createdAt":"2019-09-19T11:21:34.886Z","updatedAt":"2019-09-19T11:22:45.358Z","commentCount":3,"likeCount":16,"tags":[],"topics":["色違"],"supportedReactions":null,"withNickname":true,"reportReason":"","hiddenByAuthor":false,"meta":{"layout":"classic"},"forumName":"寶可夢","forumAlias":"pokemon","school":"五月天皮卡崙","department":"starmayday","replyTitle":null,"gender":"M","personaSubscriptable":null,"reactions":[{"id":"286f599c-f86a-4932-82f0-f5a06f1eca03","count":16}],"hidden":false,"customStyle":null,"isSuspiciousAccount":true,"layout":"classic","withImages":true,"withVideos":false,"media":[{"url":"https://i.imgur.com/LOhiOET.png"},{"url":"https://i.imgur.com/gms2BJq.png"},{"url":"https://i.imgur.com/3yPbWNB.png"}],"reportReasonText":"","mediaMeta":[{"id":"252092d1-ba89-442b-b7dc-f2926d682b5e","url":"https://i.imgur.com/LOhiOETl.jpg","normalizedUrl":"https://i.imgur.com/LOhiOETl.jpg","thumbnail":"https://i.imgur.com/LOhiOETl.jpg","type":"image/thumbnail","tags":["ANNOTATED"],"createdAt":"2019-09-19T11:21:34.886Z","updatedAt":"2019-09-19T11:22:45.358Z"},{"id":"252092d1-ba89-442b-b7dc-f2926d682b5e","url":"https://i.imgur.com/LOhiOET.png","normalizedUrl":"https://imgur.com/LOhiOET","thumbnail":"https://i.imgur.com/LOhiOETl.jpg","type":"image/imgur","tags":["ANNOTATED"],"createdAt":"2019-09-19T11:21:34.886Z","updatedAt":"2019-09-19T11:22:45.358Z"},{"id":"96ad4580-23e6-49c7-9e32-a50c8881c30f","url":"https://i.imgur.com/gms2BJq.png","normalizedUrl":"https://imgur.com/gms2BJq","thumbnail":"https://i.imgur.com/gms2BJql.jpg","type":"image/imgur","tags":["ANNOTATED"],"createdAt":"2019-09-19T11:21:34.886Z","updatedAt":"2019-09-19T11:22:45.358Z"},{"id":"1e291677-a3ea-4718-8a95-b2f966f5c6d6","url":"https://i.imgur.com/3yPbWNB.png","normalizedUrl":"https://imgur.com/3yPbWNB","thumbnail":"https://i.imgur.com/3yPbWNBl.jpg","type":"image/imgur","tags":["ANNOTATED"],"createdAt":"2019-09-19T11:21:34.886Z","updatedAt":"2019-09-19T11:22:45.358Z"}],"postAvatar":""}