{"id":232970665,"title":"intense & intensive","content":"1.\nintense, A, \n意思有“強烈的/劇烈的”跟“熱情的/熱切的”\n\n1.1 The fracture caused him intense pain. (骨折給他造成了劇烈的疼痛)\n\n1.2 The heat has grown less intense. \n(沒有先前那樣熱了)\n\n1.3 The candidate has many intense supporters. \n(這位候選人有許多熱烈的支持者)\n\n1.4 He was young and intense, and silly, too. \n(他年輕又熱情, 也有點傻氣)\n\n\n\n2. \nintensity, N, \n意思有“(電/熱/光/聲的)強度”跟“(思想/感情/活動的)強烈”\n\n2.1 Light intensity is the most important environmental factor. \n(光照強度是最重要的環境因素)\n\n2.2 The explosion was of such intensity that it was heard five miles away. \n(爆炸的威力/強度大到五英哩外都聽得到)\n\n2.3 The strike is growing in intensity. \n(罷工日益加劇)\n\n2.4 The poem showed great intensity of feeling. \n(這首詩表現出強烈的感情)\n\n\n\n3.\nintensify, V, \n意思“強化/增強/使變激烈”:\n\n3.1 The war/competition intensified. \n(戰爭/競爭變得激烈了)\n\n3.2 My first failure only intensified my desire to succeed. \n(我的初次失敗只更加強了我成功的信念)\n\n\n\n4.\n“intense” (A, “強烈的/劇烈的” + “熱情的/熱切的”)跟“intensive” (A, “加強的/密集的” + “精深的/透徹的”)的不同：\n\n“intense”強調強度，\n“intensive”強調密集程度/深入程度/徹底程度\n\n4.1 There we received several weeks of intensive training. \n(在那裡我們受了幾星期的集中訓練)\n\n4.2 Some books are for intensive study and some are for cursory reading. \n(有的書必須精讀，有的只要稍加涉獵即可)\n\n4.3 Wally was now out of danger and removed from intensive care. \n(瓦利已經脫離危險, 不再需要密集/特別護理) (intensive care unit/ICU加護病房)","excerpt":"1.，intense， A，意思有“強烈的/劇烈的”跟“熱情的/熱切的”，1.1 The fracture caused him intense pain. （骨折給他造成了劇烈的疼痛），1.2 Th","anonymousSchool":false,"anonymousDepartment":false,"pinned":false,"forumId":"e33fd5d2-025f-46e4-8b81-3f6fecdd25e1","replyId":null,"createdAt":"2020-01-28T05:30:49.467Z","updatedAt":"2020-01-28T05:30:49.467Z","commentCount":0,"likeCount":1,"tags":["HIDE_THUMBNAIL"],"topics":["歌聲英文筆記"],"supportedReactions":null,"withNickname":true,"reportReason":"","hiddenByAuthor":false,"meta":{"layout":"classic"},"forumName":"廢文","forumAlias":"whysoserious","school":"歌聲™️","department":"clintfrazier77","replyTitle":null,"gender":"M","personaSubscriptable":null,"reactions":[{"id":"286f599c-f86a-4932-82f0-f5a06f1eca03","count":1}],"hidden":false,"customStyle":null,"isSuspiciousAccount":false,"layout":"classic","withImages":false,"withVideos":false,"media":[],"reportReasonText":"","mediaMeta":[],"postAvatar":""}