{"id":232822340,"title":"給濟公師父的一把扇子","content":"元旦那天，我送給濟公師父一把扇子。\n\n自己手作的扇子，誠意滿滿對吧XD\n\n用紅色的美術紙折出扇子的形狀\n\n接著使用PP板製作握柄\n（外面再包一層金光閃閃ㄟ紙）\n\n再把扇子跟握柄給黏起來\n（perfect 非常完美👍）\n\n完成後 似乎還少了點什麼...\n\n於是乎 \n我在材料箱中找到了一張春聯\n\n還是去年貼剩下的春聯（覺得很👌）\n\n拿起剪刀把「福」字給剪了下來\n✂---✂---✂---✂---✂---✂---\n\n接著再把「福」字給貼在扇子上\n\n就大功告成啦~~（放鞭炮🎆）\n\n\n之後\n我帶著一顆虔誠的心♥\n還有那一把扇子\n去見濟公師父啦\n\n我把扇子放在供桌上\n\n點起線香拜拜\n\n拜拜的時候我忘了說一件很重要的事了😅\n\n我只有在心中默念：「祝祢們新年快樂哦~」\n\n然後就跑去外面的門旁邊插香了...\n\n欸？ 好像哪裡怪怪的...\n\n齁~~~不對啦~ \n\n我在裡面拜拜完忘記先插香了啦\n\n趕緊跑回去把線香插在香爐上（被自己打敗）\n\n過了一會兒\n\n乩身說：「濟公師父說妳要再跟祂稟告一次」\n\n我：「什麼？」\n\n乩身：「妳剛剛拜拜有跟祂說那支扇子要送給祂的嗎？」\n\n我：「啊~哈哈哈 沒有餒」\n\n我：「我只有默念說祝祢們新年快樂」\n\n乩身：「這樣濟公師父收不到啦~」\n\n我：「真的哦！？」\n\n乩身：「嘿啊~妳扇子上面也沒有寫敬獻給濟公師父的字齁？」\n\n我：「哈哈哈  沒有 」\n\n乩身：「難怪濟公師父會這樣說...」\n\n濟公師父：「我收不到那支扇子~拜拜的時候沒有向我說扇子是要送給我的，我看扇子上面也沒有寫我的名字」\n\n我：「蛤~~那怎麼辦啊~還來得及嗎？」\n\n乩身：「濟公師父說妳再跟祂說一次就可以了」\n\n我：「好，那要再拿香說一次嗎？」\n\n乩身：「不用，雙手合十說就好」\n\n我：「是大聲念出來的那種嗎？」\n\n乩身：「不用 ...妳剛剛拜拜的時候有大聲念出來嗎？」\n\n我：「哈哈  沒有」\n\n乩身：「默念就可以了」\n\n我「好哦」\n\n於是我就雙手合十默念向濟公師父說...\n\n我：「濟公師父祢好，我是信女XXX,我有做一把扇子要送給祢唷，希望祢會喜歡，祝祢新年快樂。」\n\n乩身說濟公師父也有給予我祝福的話♥\n\n濟公師父：「祝妳元旦快樂，每天幸福快樂」\n\n雖然是很簡短的話\n\n不過能得到濟公師父的祝福真的很幸運🍀\n\n話說 \n\n濟公師父收到我做的扇子應該有三把了😂\n\n打算濟公師父生日的時候\n\n我再做一把特別的扇子給祂\n\n\n由上述送扇子的事件\n\n讓我學習到了「傳達」很重要\n\n無論是與神明或是與人之間\n\n妳認為對方會曉得妳內心的想法\n\n但是妳沒有表達出來\n\n對方也許不知道妳真正的想法是什麼\n\n或是對方知道妳的想法但是想聽妳親口說 哈\n\n\n祝福大家新年快樂哦 😘\n\n\n\n\n---有個體貼小男友---","excerpt":"元旦那天，我送給濟公師父一把扇子。自己手作的扇子，誠意滿滿對吧XD，用紅色的美術紙折出扇子的形狀，接著使用PP板製作握柄，（外面再包一層金光閃閃ㄟ紙），再把扇子跟握柄給黏起來，（perfect 非常完","anonymousSchool":false,"anonymousDepartment":false,"pinned":false,"forumId":"37a78696-f6a6-48ec-a19f-688f799a2aed","replyId":null,"createdAt":"2020-01-04T05:11:08.595Z","updatedAt":"2020-01-04T12:03:30.415Z","commentCount":16,"likeCount":146,"tags":[],"topics":["親身經歷","真實故事","神明","濟公","扇子"],"supportedReactions":null,"withNickname":true,"reportReason":"","hiddenByAuthor":false,"meta":{"layout":"classic"},"forumName":"靈異","forumAlias":"marvel","school":"有個體貼小男友","department":"sunmer","replyTitle":null,"gender":"M","personaSubscriptable":true,"reactions":[{"id":"286f599c-f86a-4932-82f0-f5a06f1eca03","count":146}],"hidden":false,"customStyle":null,"isSuspiciousAccount":false,"layout":"classic","withImages":false,"withVideos":false,"media":[],"reportReasonText":"","mediaMeta":[],"postAvatar":""}