{"id":232702198,"title":"恐怖腦詹迷又在酸公鹿了","content":"我這邊不針對理性詹迷\n但某些喪心病狂的腦詹迷你們是不是垃圾啊?\n以前Kobe地位在LBJ之上你們就瘋狂酸他打鐵\n後來rose中斷LBJ連續mvp你們就酸他史上最弱mvp\n之後KD拿MVP你們就酸他黑哨黑雷（LBJ不也是靠黑哨走步都沒吹）\n到後來勇士從LBJ手上拿三冠你們就酸curry娘炮勇士黑哨(LBJ自己17年冠軍賽單節22罰黑成那樣還輸球)\n到今年可愛選擇快艇不去湖人幫LBJ捧覽趴你們就罵他心機仔\n到現在公鹿中斷連勝戰績被湖人超車你們又再酸字母哥過譽\n\n我他媽請問你們下一個要酸誰???\n77??吹樣??鉛筆???\n是不是只要威脅你們主子LBJ的通通都要被蝦機巴亂酸一遍?","excerpt":"我這邊不針對理性詹迷，但某些喪心病狂的腦詹迷你們是不是垃圾啊？以前Kobe地位在LBJ之上你們就瘋狂酸他打鐵，後來rose中斷LBJ連續mvp你們就酸他史上最弱mvp，之後KD拿MVP你們就酸他黑哨黑","anonymousSchool":false,"anonymousDepartment":false,"pinned":false,"forumId":"863b960a-72a8-4479-80a2-b976275c002e","replyId":null,"createdAt":"2019-12-17T04:37:44.281Z","updatedAt":"2019-12-17T12:13:05.450Z","commentCount":29,"likeCount":6,"tags":[],"topics":["NBA","籃球","詹迷出征吋草不生","詹迷素質","LBJ"],"supportedReactions":null,"withNickname":true,"reportReason":"","hiddenByAuthor":false,"meta":{"layout":"classic"},"forumName":"籃球","forumAlias":"basketball","school":"垃圾廢物私立學店詹迷韓粉","department":"handsome_178","replyTitle":null,"gender":"M","personaSubscriptable":false,"reactions":[{"id":"286f599c-f86a-4932-82f0-f5a06f1eca03","count":6}],"hidden":false,"customStyle":null,"isSuspiciousAccount":false,"layout":"classic","withImages":false,"withVideos":false,"media":[],"reportReasonText":"","mediaMeta":[],"postAvatar":""}