{"id":232783644,"title":"蘆竹運動中心","content":"蘆竹運動中心開了真的大開我眼界，健身房這麼小還這麼多隔間，每個月還要收1500，淋浴間設計也是奇葩，置衣架洗澡順便洗衣服，鏡子小到找不到，浴室不多裝排水孔現在變成裝防水條，原本滿心期待要去那邊運動，看完之後覺得蔬菜除了風評不太好，設備不錯跟588月費真的是佛心來的。","excerpt":"蘆竹運動中心開了真的大開我眼界，健身房這麼小還這麼多隔間，每個月還要收1500，淋浴間設計也是奇葩，置衣架洗澡順便洗衣服，鏡子小到找不到，浴室不多裝排水孔現在變成裝防水條，原本滿心期待要去那邊運動，看","anonymousSchool":false,"anonymousDepartment":true,"pinned":false,"forumId":"9b5213d6-4427-4a3c-b788-efa19493631c","replyId":null,"createdAt":"2019-12-29T11:38:09.552Z","updatedAt":"2019-12-29T11:38:09.552Z","commentCount":36,"likeCount":11,"tags":["HIDE_THUMBNAIL"],"topics":["運動","健身房","重訓","健身","蘆竹"],"supportedReactions":null,"withNickname":false,"reportReason":"","hiddenByAuthor":false,"meta":{"layout":"classic"},"forumName":"健身","forumAlias":"fitness","school":"國立臺灣海洋大學","replyTitle":null,"gender":"M","personaSubscriptable":false,"reactions":[{"id":"286f599c-f86a-4932-82f0-f5a06f1eca03","count":11}],"hidden":false,"customStyle":null,"isSuspiciousAccount":false,"layout":"classic","withImages":false,"withVideos":false,"media":[],"reportReasonText":"","mediaMeta":[],"postAvatar":""}