{"id":232499963,"title":"#問 假日/逢甲過夜停車","content":"請問板上各位大大們\n因為假日爸媽要開車來台中玩\n晚上要住在逢甲\n但停車要停過夜 爬了網路文章\n說福星路上很多都要留鑰匙，而且收費很黑，這樣有點不放心\n目前有找到 \n\n\n\n1.東門的 河北停車場\n*優點：便宜/例假日最高收到100\n*缺點：戶外式/離家有一段距離（住西安街）\n\n2.學校體育館的停車場\n*優點：室內/離家近\n*缺點：單日最高收到300\n\n**另外想請問，如果開車沒有申請停車證，是直接開進去體館地下停車場就可以了嗎？**\n\n感謝各位解答～～預祝大家都歐趴❤️❤️❤️❤️","excerpt":"請問板上各位大大們，因為假日爸媽要開車來台中玩，晚上要住在逢甲，但停車要停過夜 爬了網路文章，說福星路上很多都要留鑰匙，而且收費很黑，這樣有點不放心，目前有找到，1.東門的 河北停車場，*優點：便宜/","anonymousSchool":false,"anonymousDepartment":true,"pinned":false,"forumId":"6f72a221-b46c-4f1e-9d82-26378d407608","replyId":null,"createdAt":"2019-11-14T06:35:10.476Z","updatedAt":"2019-11-14T06:35:37.542Z","commentCount":11,"likeCount":6,"tags":["HIDE_THUMBNAIL"],"topics":["假日","過夜","停車"],"supportedReactions":null,"withNickname":false,"reportReason":"","hiddenByAuthor":false,"meta":{"layout":"classic"},"forumName":"逢甲大學","forumAlias":"fcu","school":"逢甲大學","replyTitle":null,"gender":"F","personaSubscriptable":true,"reactions":[{"id":"286f599c-f86a-4932-82f0-f5a06f1eca03","count":6}],"hidden":false,"customStyle":null,"isSuspiciousAccount":false,"layout":"classic","withImages":false,"withVideos":false,"media":[],"reportReasonText":"","mediaMeta":[],"postAvatar":""}