{"id":233009084,"title":"奉勸各位","content":"喜歡不能當飯吃\n不能當一個理由\n不能當一個堅持\n\n為什麼？\n因為終究會被不適合暴打\n\n可好笑的事情 就是你真的很喜歡人家\n寧可被暴打一陣子\n寧可等到被宣判到我們不適合\n才甘願收手作罷","excerpt":"喜歡不能當飯吃，不能當一個理由，不能當一個堅持，為什麼？因為終究會被不適合暴打，可好笑的事情 就是你真的很喜歡人家，寧可被暴打一陣子，寧可等到被宣判到我們不適合，才甘願收手作罷","anonymousSchool":true,"anonymousDepartment":true,"pinned":false,"forumId":"b5b2653a-6304-4564-9ea0-a4cec0be7aee","replyId":null,"createdAt":"2020-02-03T12:46:45.182Z","updatedAt":"2020-02-03T12:46:45.182Z","commentCount":3,"likeCount":33,"tags":["HIDE_THUMBNAIL"],"topics":["崩潰"],"supportedReactions":null,"withNickname":false,"reportReason":"","hiddenByAuthor":false,"meta":{"layout":"classic"},"forumName":"彩虹","forumAlias":"rainbow","replyTitle":null,"gender":"F","personaSubscriptable":false,"reactions":[{"id":"286f599c-f86a-4932-82f0-f5a06f1eca03","count":33}],"hidden":false,"customStyle":null,"isSuspiciousAccount":false,"layout":"classic","withImages":false,"withVideos":false,"media":[],"reportReasonText":"","mediaMeta":[],"postAvatar":""}