{"id":232560602,"title":"在選輕檔車","content":"昨天通宵看了整夜的車\n想要請問r15v3 cbr150r 小阿魯\n小阿魯我可能沒辦法檔檔萬轉_(:_」∠)_\n可是發現另外兩台都只能買水貨\n而且r15v3好像容易出狀況（？）\ncbr150r主要是信仰（X)\n目前還沒打算上黃紅牌，還沒很熟悉檔車\n怕說真實上路有危險啥的\n182/88\n小阿魯對我來說真的太小台，不過看在維修便宜（相比之下）對我比較有吸引力\n剩下兩台後續保養的費用大概是多少，有人清楚嗎？\n都爬過文章ㄌ，可是沒有找到確切金額 嗚嗚嗚","excerpt":"昨天通宵看了整夜的車，想要請問r15v3 cbr150r 小阿魯，小阿魯我可能沒辦法檔檔萬轉_（：_」∠）_，可是發現另外兩台都只能買水貨，而且r15v3好像容易出狀況（？），cbr150r主要是信仰","anonymousSchool":false,"anonymousDepartment":true,"pinned":false,"forumId":"2cffc289-d332-4d4e-95a7-cae58a1778aa","replyId":null,"createdAt":"2019-11-24T04:12:44.417Z","updatedAt":"2019-11-24T04:12:44.417Z","commentCount":24,"likeCount":31,"tags":["HIDE_THUMBNAIL"],"topics":["檔車","重機","重機板","輕檔車","Honda"],"supportedReactions":null,"withNickname":false,"reportReason":"","hiddenByAuthor":false,"meta":{"layout":"classic"},"forumName":"重機","forumAlias":"heavy_motorcycle","school":"慈惠醫護管理專科學校","replyTitle":null,"gender":"M","personaSubscriptable":null,"reactions":[{"id":"286f599c-f86a-4932-82f0-f5a06f1eca03","count":31}],"hidden":false,"customStyle":null,"isSuspiciousAccount":false,"layout":"classic","withImages":false,"withVideos":false,"media":[],"reportReasonText":"","mediaMeta":[],"postAvatar":""}