{"id":232675908,"title":"朋友異國結婚該包多少？","content":"收到明年9月兩場婚禮的邀約\n都是曾經是同學的朋友婚禮\n感情都算比點頭之交好\n但不會常常聯絡、一聯絡就會隨便聊聊的那種\n\n一位是在新加坡結婚\n一位是在泰國結婚\n（兩個朋友都不是台灣人）\n都是在高級飯店婚宴\n\n目前因為工作關係安排\n有告知兩方可能不能出席婚禮\n但有打算包紅包給她們\n另外如果知道是能出席的\n我也會最晚二月通知她們\n\n想問大家有沒有類似經驗⋯\n要花機票錢+住宿費去參加婚禮\n這樣還該包多少給她們？\n\n我另一位新加坡朋友說\n新加坡飯店婚宴都挺高級的\n一個人最少最少也該包$200-300 新幣\n（台幣匯率大約 = $4500-$6600）\n泰國也差不多\n\n那如果沒有出席婚禮\n我也該包一樣的行情給她們嗎？\n還是送禮物就也可以？\n\n如果有出席，我有打算帶一位家人或男友一起去\n兩個人頭的紅包都會是我出\n所以⋯ 機票+飯店+紅包 x 2場婚禮\n數字挺可觀的(つД`)ノ\n對我是大出血\n可能那陣子會很節省的渡過⋯ \n最後，我離結婚還有點遠不知道未來會不會邀請她們⋯","excerpt":"收到明年9月兩場婚禮的邀約，都是曾經是同學的朋友婚禮，感情都算比點頭之交好，但不會常常聯絡、一聯絡就會隨便聊聊的那種，一位是在新加坡結婚，一位是在泰國結婚，（兩個朋友都不是台灣人），都是在高級飯店婚宴","anonymousSchool":true,"anonymousDepartment":true,"pinned":false,"forumId":"f11e8d02-6756-4376-9db3-e1cca4d2a66c","replyId":null,"createdAt":"2019-12-12T17:30:15.432Z","updatedAt":"2019-12-12T17:33:24.273Z","commentCount":14,"likeCount":10,"tags":["HIDE_THUMBNAIL"],"topics":["異國","婚禮","紅包禮金"],"supportedReactions":null,"withNickname":false,"reportReason":"","hiddenByAuthor":false,"meta":{"layout":"classic"},"forumName":"結婚","forumAlias":"marriage","replyTitle":null,"gender":"F","personaSubscriptable":true,"reactions":[{"id":"286f599c-f86a-4932-82f0-f5a06f1eca03","count":10}],"hidden":false,"customStyle":null,"isSuspiciousAccount":false,"layout":"classic","withImages":false,"withVideos":false,"media":[],"reportReasonText":"","mediaMeta":[],"postAvatar":""}