{"id":232922868,"title":"婚前婚後","content":"在結婚前，老公不管上班到幾點，只要一下班都會趕回家陪我\n  婚後有了小孩，他都早出晚歸，每天都跟我說要工作很忙，就連假日也說要加班，我一直都很相信他，我知道他工作很辛苦，但我每天在家一個人顧小孩也很悶啊\n\n  總是覺得我很閒就什麼事都丟給我做，我如果反駁他，他就會說我要工作很忙很累，我因為跟他結婚生子放棄我自由的生活，因為家裡經濟不是很寬裕，不能出去賺錢只好在家顧小孩\n\n  每天都被綁在家，不能做自己想做的事，還要忍受他把家當旅館，整天要他做甚麼他只會跟我喊累，每天看到他在家時間只有短短8小時，讓我感覺我地位好像越來越低，因為小孩根本抽不開身，不然我也想去工作，我才23歲而已都還沒出過社會，真的真的好後悔跟他結婚\n\n每天每天都很想離婚，你們婚後生活如何呢？","excerpt":"在結婚前，老公不管上班到幾點，只要一下班都會趕回家陪我，婚後有了小孩，他都早出晚歸，每天都跟我說要工作很忙，就連假日也說要加班，我一直都很相信他，我知道他工作很辛苦，但我每天在家一個人顧小孩也很悶啊，","anonymousSchool":true,"anonymousDepartment":true,"pinned":false,"forumId":"f11e8d02-6756-4376-9db3-e1cca4d2a66c","replyId":null,"createdAt":"2020-01-20T00:32:49.013Z","updatedAt":"2020-01-20T00:32:49.013Z","commentCount":43,"likeCount":42,"tags":[],"topics":["婚姻生活","迷惘","心情"],"supportedReactions":null,"withNickname":false,"reportReason":"","hiddenByAuthor":false,"meta":{"layout":"classic"},"forumName":"結婚","forumAlias":"marriage","replyTitle":null,"gender":"F","personaSubscriptable":null,"reactions":[{"id":"286f599c-f86a-4932-82f0-f5a06f1eca03","count":41},{"id":"514c2569-fd53-4d9d-a415-bf0f88e7329f","count":1}],"hidden":false,"customStyle":null,"isSuspiciousAccount":false,"layout":"classic","withImages":false,"withVideos":false,"media":[],"reportReasonText":"","mediaMeta":[],"postAvatar":""}