{"id":232971066,"title":"凹嗚狼人殺 vs Godlie","content":"凹嗚狼人殺:\n1.娛樂百分百單元\n2.大多為10人局\n3.歡樂 快速攻防的風格\n\nGodlie:\n1.狼人殺實境秀遊戲\n2.12人警長局\n3.一局最少1小時半 緩慢 沉穩的分析戰\n\n比起娛百的狼人殺單元\ngodlie是專為狼人殺設計的實境秀遊戲節目\n強度也比娛百高出一截\n不認真看很容易看不懂邏輯\n角色也比娛百多","excerpt":"凹嗚狼人殺：1.娛樂百分百單元，2.大多為10人局，3.歡樂 快速攻防的風格，Godlie：1.狼人殺實境秀遊戲，2.12人警長局，3.一局最少1小時半 緩慢 沉穩的分析戰，比起娛百的狼人殺單元，go","anonymousSchool":false,"anonymousDepartment":true,"pinned":false,"forumId":"ba0145a2-adff-4229-9a84-9b26ebd2f7f0","replyId":null,"createdAt":"2020-01-28T07:00:31.926Z","updatedAt":"2020-01-28T07:01:54.253Z","commentCount":6,"likeCount":17,"tags":[],"topics":["狼人殺"],"supportedReactions":null,"withNickname":false,"reportReason":"","hiddenByAuthor":false,"meta":{"layout":"classic"},"forumName":"戲劇綜藝","forumAlias":"tvepisode","school":"輔仁大學","replyTitle":null,"gender":"M","personaSubscriptable":false,"reactions":[{"id":"286f599c-f86a-4932-82f0-f5a06f1eca03","count":17}],"hidden":false,"customStyle":null,"isSuspiciousAccount":false,"layout":"classic","withImages":false,"withVideos":false,"media":[],"reportReasonText":"","mediaMeta":[],"postAvatar":""}